crowdsec_fastly_bouncer-0.4.0.dist-info/licenses/LICENSE
fastly_bouncer/__init__.py
fastly_bouncer/config.py
fastly_bouncer/fastly_api.py
fastly_bouncer/main.py
fastly_bouncer/service.py
fastly_bouncer/utils.py
fastly_bouncer/vcl_templates.py
crowdsec_fastly_bouncer-0.4.0.dist-info/METADATA
crowdsec_fastly_bouncer-0.4.0.dist-info/WHEEL
crowdsec_fastly_bouncer-0.4.0.dist-info/entry_points.txt
crowdsec_fastly_bouncer-0.4.0.dist-info/top_level.txt
crowdsec_fastly_bouncer-0.4.0.dist-info/RECORD
