Metadata-Version: 2.4
Name: crowdsec-fastly-bouncer
Version: 0.4.0
Summary: CrowdSec Fastly bouncer
Home-page: https://github.com/crowdsecurity/cs-fastly-bouncer
Author: CrowdSec
Author-email: core.tech@crowdsec.net
Project-URL: Bug Tracker, https://github.com/crowdsecurity/cs-fastly-bouncer/issues
Classifier: Programming Language :: Python :: 3
Classifier: License :: OSI Approved :: MIT License
Classifier: Operating System :: OS Independent
Requires-Python: >=3.6
License-File: LICENSE
Requires-Dist: pyyaml
Requires-Dist: python-dateutil
Requires-Dist: trio
Requires-Dist: pycrowdsec
Requires-Dist: httpx
Dynamic: license-file
